stitch_generator/__init__.py
stitch_generator/collection/__init__.py
stitch_generator/collection/functions/__init__.py
stitch_generator/collection/functions/functions_1d.py
stitch_generator/collection/motifs/__init__.py
stitch_generator/collection/motifs/collection.py
stitch_generator/collection/motifs/satin_circle.py
stitch_generator/collection/motifs/square_spiral.py
stitch_generator/collection/stitch_effects/__init__.py
stitch_generator/collection/stitch_effects/decorative_stitches.py
stitch_generator/collection/stitch_effects/stitch_effects.py
stitch_generator/collection/stitch_effects/underlays.py
stitch_generator/collection/subdivision/__init__.py
stitch_generator/collection/subdivision/collection.py
stitch_generator/collection/subdivision/subdivision_with_varying_offset.py
stitch_generator/collection/subdivision/subdivison_with_varying_alignment.py
stitch_generator/collection/subdivision/tatami.py
stitch_generator/framework/__init__.py
stitch_generator/framework/path.py
stitch_generator/framework/stitch_effect.py
stitch_generator/framework/types.py
stitch_generator/functions/__init__.py
stitch_generator/functions/add_gap.py
stitch_generator/functions/arc_length_mapping.py
stitch_generator/functions/ensure_shape.py
stitch_generator/functions/estimate_length.py
stitch_generator/functions/function_1d_stairs.py
stitch_generator/functions/function_modifiers.py
stitch_generator/functions/function_sequence.py
stitch_generator/functions/functions_1d.py
stitch_generator/functions/functions_2d.py
stitch_generator/functions/functions_3d.py
stitch_generator/functions/motif_generators.py
stitch_generator/functions/noise.py
stitch_generator/shapes/__init__.py
stitch_generator/shapes/bezier.py
stitch_generator/shapes/circle.py
stitch_generator/shapes/ellipse.py
stitch_generator/shapes/line.py
stitch_generator/shapes/rounded_rect.py
stitch_generator/shapes/spiral.py
stitch_generator/stitch_effects/__init__.py
stitch_generator/stitch_effects/path_effects/__init__.py
stitch_generator-0.1.0.dist-info/METADATA
stitch_generator-0.1.0.dist-info/WHEEL
stitch_generator-0.1.0.dist-info/licenses/LICENSE
stitch_generator-0.1.0.dist-info/RECORD
