Metadata-Version: 2.1
Name: stitch_generator
Version: 0.1.0
Summary: Stitch generator for machine embroidery
Project-URL: Homepage, https://github.com/bastanja/stitch_generator
Author-email: Tanja Bast <tanja.s.bast@gmail.com>
License: MIT License
License-File: LICENSE
Classifier: License :: OSI Approved :: MIT License
Classifier: Operating System :: OS Independent
Classifier: Programming Language :: Python :: 3
Requires-Python: >=3.7
Requires-Dist: noise
Requires-Dist: numpy
Requires-Dist: scipy
Provides-Extra: test
Requires-Dist: coverage; extra == 'test'
Requires-Dist: pytest; extra == 'test'
